jc_handy_exiftool/__init__.py
jc_handy_exiftool/exiftool.py
jc_handy_exiftool-1.0.4.dist-info/LICENSE
jc_handy_exiftool-1.0.4.dist-info/METADATA
jc_handy_exiftool-1.0.4.dist-info/WHEEL
jc_handy_exiftool-1.0.4.dist-info/top_level.txt
jc_handy_exiftool-1.0.4.dist-info/RECORD
